subtensorapi/__init__.py
subtensorapi/__main__.py
subtensorapi/cli.py
subtensorapi/exceptions.py
subtensorapi/bin/subtensor-node-api-linux
subtensorapi-1.1.0.dist-info/LICENSE
subtensorapi-1.1.0.dist-info/METADATA
subtensorapi-1.1.0.dist-info/WHEEL
subtensorapi-1.1.0.dist-info/top_level.txt
subtensorapi-1.1.0.dist-info/RECORD
