Metadata-Version: 2.1
Name: subtensorapi
Version: 1.1.0
Summary: Subtensor API package for bittensor
Author-email: Opentensor Foundation <cameron@opentensor.ai>, Opentensor Foundation <eduardo@opentensor.ai>
License: MIT
Project-URL: Documentation, https://github.com/opentensor/subtensor-api#subtensor-api
Project-URL: Source, https://github.com/opentensor/subtensor-api
Platform: UNKNOWN
Requires-Python: >=3.7
License-File: LICENSE
Provides-Extra: test
Requires-Dist: unittest ; extra == 'test'
